MetaCerberus-1.4.0.data/scripts/metacerberus.py
MetaCerberus-1.4.0.data/scripts/pathview-metacerberus.R
MetaCerberus-1.4.0.data/scripts/ray-slurm-metacerberus.sh
meta_cerberus/Chunker.py
meta_cerberus/__init__.py
meta_cerberus/metacerberus.config
meta_cerberus/metacerberus_decon.py
meta_cerberus/metacerberus_formatFasta.py
meta_cerberus/metacerberus_genecall.py
meta_cerberus/metacerberus_hmm.py
meta_cerberus/metacerberus_logo.jpg
meta_cerberus/metacerberus_merge.py
meta_cerberus/metacerberus_metastats.py
meta_cerberus/metacerberus_parser.py
meta_cerberus/metacerberus_prostats.py
meta_cerberus/metacerberus_qc.py
meta_cerberus/metacerberus_report.py
meta_cerberus/metacerberus_setup.py
meta_cerberus/metacerberus_trim.py
meta_cerberus/metacerberus_visual.py
meta_cerberus/plotly-2.0.0.min.js
meta_cerberus/style.css
meta_cerberus/DB/databases.tsv
meta_cerberus/FGS/FragGeneScanRS-Darwin.tar.gz
meta_cerberus/FGS/FragGeneScanRS-Linux.tar.gz
meta_cerberus/__pycache__/__init__.cpython-39.pyc
meta_cerberus/__pycache__/metacerberus_decon.cpython-39.pyc
meta_cerberus/__pycache__/metacerberus_formatFasta.cpython-39.pyc
meta_cerberus/__pycache__/metacerberus_genecall.cpython-39.pyc
meta_cerberus/__pycache__/metacerberus_hmm.cpython-39.pyc
meta_cerberus/__pycache__/metacerberus_merge.cpython-39.pyc
meta_cerberus/__pycache__/metacerberus_metastats.cpython-39.pyc
meta_cerberus/__pycache__/metacerberus_parser.cpython-39.pyc
meta_cerberus/__pycache__/metacerberus_prostats.cpython-39.pyc
meta_cerberus/__pycache__/metacerberus_qc.cpython-39.pyc
meta_cerberus/__pycache__/metacerberus_report.cpython-39.pyc
meta_cerberus/__pycache__/metacerberus_setup.cpython-39.pyc
meta_cerberus/__pycache__/metacerberus_trim.cpython-39.pyc
meta_cerberus/__pycache__/metacerberus_visual.cpython-39.pyc
meta_cerberus/dependency_files/PacBio_quality-control.fna
meta_cerberus/dependency_files/adapters.fna
meta_cerberus/dependency_files/lambda-phage.fna
meta_cerberus/dependency_files/phix174_ill.ref.fna
MetaCerberus-1.4.0.dist-info/LICENSE.txt
MetaCerberus-1.4.0.dist-info/METADATA
MetaCerberus-1.4.0.dist-info/WHEEL
MetaCerberus-1.4.0.dist-info/top_level.txt
MetaCerberus-1.4.0.dist-info/RECORD
