Metadata-Version: 2.1
Name: MetaCerberus
Version: 1.4.0
Summary: Versatile Functional Ontology Assignments for Metagenomes via Hidden Markov Model (HMM) searching with environmental focus of shotgun meta'omics data
Home-page: https://github.com/raw-lab/metacerberus
Author: Jose L. Figueroa III, Richard A. White III
Author-email: jlfiguer@uncc.edu
License: BSD License
Platform: Unix
Classifier: Development Status :: 5 - Production/Stable
Classifier: Programming Language :: Python :: 3
Classifier: Programming Language :: Python :: 3.8
Classifier: Programming Language :: Python :: 3.9
Classifier: Programming Language :: Python :: 3.10
Classifier: Programming Language :: Python :: 3.11
Classifier: Programming Language :: Python :: 3.12
Classifier: License :: OSI Approved :: BSD License
Classifier: Operating System :: Unix
Requires-Python: >=3.8
License-File: LICENSE.txt
Requires-Dist: setuptools
Requires-Dist: pandas
Requires-Dist: pyhmmer
Requires-Dist: hydrampp
Requires-Dist: pyrodigal
Requires-Dist: pyrodigal-gv
Requires-Dist: configargparse
Requires-Dist: metaomestats
Requires-Dist: kaleido
Requires-Dist: scikit-learn
Requires-Dist: plotly
Requires-Dist: psutil
Requires-Dist: dominate
